{
  "movie_id": "1292370",
  "rank": 48,
  "reviews": [
    {
      "username": "cici0617",
      "star": "4"
    },
    {
      "username": "kriek",
      "star": "4"
    },
    {
      "username": "wangqt",
      "star": "5"
    },
    {
      "username": "wyshare",
      "star": "5"
    },
    {
      "username": "UptoNana",
      "star": "5"
    },
    {
      "username": "breakmia",
      "star": "5"
    },
    {
      "username": "beemer",
      "star": "5"
    },
    {
      "username": "Gongzi_.Fox",
      "star": "5"
    },
    {
      "username": "kid131",
      "star": "5"
    },
    {
      "username": "TYPE-MOON",
      "star": "5"
    },
    {
      "username": "1389165",
      "star": "3"
    },
    {
      "username": "vitayangl",
      "star": "4"
    },
    {
      "username": "yhaw",
      "star": "5"
    },
    {
      "username": "1224581",
      "star": "4"
    },
    {
      "username": "1062080",
      "star": "4"
    },
    {
      "username": "2760432",
      "star": "4"
    },
    {
      "username": "sensitivebastar",
      "star": "5"
    },
    {
      "username": "qfmeng",
      "star": "5"
    },
    {
      "username": "LiuXiao8",
      "star": "4"
    },
    {
      "username": "x21",
      "star": "1"
    },
    {
      "username": "gilian",
      "star": "5"
    },
    {
      "username": "behappykelly",
      "star": "5"
    },
    {
      "username": "posthumus",
      "star": "5"
    },
    {
      "username": "acemore",
      "star": "5"
    },
    {
      "username": "4194270",
      "star": "2"
    },
    {
      "username": "Hoary",
      "star": "5"
    },
    {
      "username": "1067837",
      "star": "5"
    },
    {
      "username": "red520",
      "star": "3"
    },
    {
      "username": "corner.crying",
      "star": "5"
    },
    {
      "username": "xiaosuflying",
      "star": "5"
    },
    {
      "username": "ardai",
      "star": "3"
    },
    {
      "username": "lipan",
      "star": "5"
    },
    {
      "username": "lllhw",
      "star": "4"
    },
    {
      "username": "ristinehe",
      "star": "5"
    },
    {
      "username": "oldtime",
      "star": "4"
    },
    {
      "username": "shuijian",
      "star": "4"
    },
    {
      "username": "nalakahn",
      "star": "5"
    },
    {
      "username": "chinapm",
      "star": "4"
    },
    {
      "username": "wxfmhan",
      "star": "5"
    },
    {
      "username": "duoz",
      "star": "5"
    },
    {
      "username": "franklintTNHWJ",
      "star": "5"
    },
    {
      "username": "be_here",
      "star": "4"
    },
    {
      "username": "khakiwu",
      "star": "3"
    },
    {
      "username": "46986910",
      "star": "5"
    },
    {
      "username": "chaojimogu",
      "star": "5"
    },
    {
      "username": "Why_314",
      "star": "5"
    },
    {
      "username": "kingsunn",
      "star": "4"
    },
    {
      "username": "1816619",
      "star": "5"
    },
    {
      "username": "2715090",
      "star": "3"
    },
    {
      "username": "jiaoxiongxin",
      "star": "5"
    },
    {
      "username": "beforeleave",
      "star": "5"
    },
    {
      "username": "2066744",
      "star": "3"
    },
    {
      "username": "ppip",
      "star": "3"
    },
    {
      "username": "2319090",
      "star": "5"
    },
    {
      "username": "3946407",
      "star": "3"
    },
    {
      "username": "emily427",
      "star": "5"
    },
    {
      "username": "4197751",
      "star": "5"
    },
    {
      "username": "ilica_in_summer",
      "star": "4"
    },
    {
      "username": "emma0917",
      "star": "5"
    },
    {
      "username": "huangzhenhao",
      "star": "5"
    },
    {
      "username": "hmy0705",
      "star": "5"
    },
    {
      "username": "29378168",
      "star": "5"
    },
    {
      "username": "Babeangel",
      "star": "4"
    },
    {
      "username": "topbenben",
      "star": "5"
    },
    {
      "username": "doristears",
      "star": "4"
    },
    {
      "username": "fennie",
      "star": "5"
    },
    {
      "username": "mysecretgarden",
      "star": "4"
    },
    {
      "username": "daoyansui",
      "star": "4"
    },
    {
      "username": "1318594",
      "star": "5"
    },
    {
      "username": "Sara0623",
      "star": "4"
    },
    {
      "username": "3900294",
      "star": "5"
    },
    {
      "username": "shenjiake",
      "star": "5"
    },
    {
      "username": "xiaoxiaonong",
      "star": "5"
    },
    {
      "username": "zeme",
      "star": "5"
    },
    {
      "username": "janice5680",
      "star": "5"
    },
    {
      "username": "mybutterfly",
      "star": "4"
    },
    {
      "username": "40460781",
      "star": "4"
    },
    {
      "username": "13974066",
      "star": "5"
    },
    {
      "username": "50348356",
      "star": 0
    },
    {
      "username": "photobiotic",
      "star": 0
    },
    {
      "username": "4279532",
      "star": "5"
    },
    {
      "username": "39133560",
      "star": "5"
    },
    {
      "username": "Jusmine",
      "star": "5"
    },
    {
      "username": "xhh1992",
      "star": "5"
    },
    {
      "username": "EMIIINEM",
      "star": "5"
    },
    {
      "username": "48355676",
      "star": "4"
    },
    {
      "username": "imcici",
      "star": "5"
    },
    {
      "username": "littlemata",
      "star": "5"
    },
    {
      "username": "2548848",
      "star": "5"
    },
    {
      "username": "godisinmyheart",
      "star": "4"
    },
    {
      "username": "teatea0512",
      "star": "5"
    },
    {
      "username": "2417320",
      "star": "5"
    },
    {
      "username": "dashudashu",
      "star": "5"
    },
    {
      "username": "ljlww191",
      "star": "5"
    },
    {
      "username": "gereisi",
      "star": "3"
    },
    {
      "username": "1360383",
      "star": "4"
    },
    {
      "username": "drinking",
      "star": "5"
    },
    {
      "username": "cynthia1230",
      "star": "4"
    },
    {
      "username": "zjas",
      "star": "5"
    },
    {
      "username": "NotReally",
      "star": "5"
    },
    {
      "username": "1689636",
      "star": "1"
    },
    {
      "username": "Felven",
      "star": "5"
    },
    {
      "username": "tantalusvbj",
      "star": "5"
    },
    {
      "username": "3906512",
      "star": "3"
    },
    {
      "username": "baixg",
      "star": "5"
    },
    {
      "username": "Q_Qiu",
      "star": "5"
    },
    {
      "username": "Keitm",
      "star": "3"
    },
    {
      "username": "abdalla",
      "star": "5"
    },
    {
      "username": "orangelee",
      "star": "4"
    },
    {
      "username": "1155606",
      "star": "4"
    },
    {
      "username": "58211668",
      "star": "5"
    },
    {
      "username": "71911451",
      "star": "5"
    },
    {
      "username": "48762841",
      "star": "5"
    },
    {
      "username": "zicenn",
      "star": "4"
    },
    {
      "username": "zicenn",
      "star": "4"
    },
    {
      "username": "zicenn",
      "star": "4"
    },
    {
      "username": "baicaitai",
      "star": "5"
    },
    {
      "username": "zhong13211",
      "star": "4"
    },
    {
      "username": "zhouzhenni",
      "star": "5"
    },
    {
      "username": "2058859",
      "star": "4"
    },
    {
      "username": "kingfish",
      "star": "4"
    },
    {
      "username": "1274609",
      "star": "5"
    },
    {
      "username": "wuaifeiwei",
      "star": "4"
    },
    {
      "username": "lynnzhou1126",
      "star": "5"
    },
    {
      "username": "cemayangmei",
      "star": "4"
    },
    {
      "username": "hddlj2046",
      "star": "5"
    },
    {
      "username": "mike_d",
      "star": "4"
    },
    {
      "username": "1103094",
      "star": "5"
    },
    {
      "username": "Lucia_xiao",
      "star": "5"
    },
    {
      "username": "vivienbaggio",
      "star": "4"
    },
    {
      "username": "cacbcy",
      "star": "4"
    },
    {
      "username": "onlywriting",
      "star": "4"
    },
    {
      "username": "lucky_luke",
      "star": "5"
    },
    {
      "username": "34181365",
      "star": "5"
    },
    {
      "username": "QQbao",
      "star": "5"
    },
    {
      "username": "lolitahz",
      "star": "5"
    },
    {
      "username": "27562856",
      "star": "5"
    },
    {
      "username": "standbyhocc",
      "star": "5"
    },
    {
      "username": "troy901010",
      "star": 0
    },
    {
      "username": "4805946",
      "star": 0
    },
    {
      "username": "xianyuxd",
      "star": "5"
    },
    {
      "username": "FLYTOTHEND",
      "star": "5"
    },
    {
      "username": "xiaoxiaopaomo",
      "star": "4"
    },
    {
      "username": "51415763",
      "star": "4"
    },
    {
      "username": "50161881",
      "star": "4"
    },
    {
      "username": "qqz42",
      "star": "4"
    },
    {
      "username": "43663749",
      "star": "5"
    },
    {
      "username": "karmaused",
      "star": "5"
    },
    {
      "username": "bri",
      "star": "4"
    },
    {
      "username": "1416974",
      "star": "4"
    },
    {
      "username": "47864122",
      "star": "4"
    },
    {
      "username": "vanjuta",
      "star": "5"
    },
    {
      "username": "famma",
      "star": "5"
    },
    {
      "username": "xiachaodongzhi",
      "star": "5"
    },
    {
      "username": "nana.qi",
      "star": "2"
    },
    {
      "username": "niking",
      "star": "5"
    },
    {
      "username": "Azz",
      "star": "5"
    },
    {
      "username": "wnfrdshao",
      "star": "5"
    },
    {
      "username": "xuepiaoliandong",
      "star": "4"
    },
    {
      "username": "1954492",
      "star": 0
    },
    {
      "username": "PennyChan",
      "star": "4"
    },
    {
      "username": "1290829",
      "star": "4"
    },
    {
      "username": "schyde",
      "star": "5"
    },
    {
      "username": "1511882",
      "star": "4"
    },
    {
      "username": "2142870",
      "star": "4"
    },
    {
      "username": "shizhuofeng",
      "star": "5"
    },
    {
      "username": "happyjunjun",
      "star": "5"
    },
    {
      "username": "1830056",
      "star": "4"
    },
    {
      "username": "shynloc",
      "star": "4"
    },
    {
      "username": "4370686",
      "star": "5"
    },
    {
      "username": "TPC",
      "star": "5"
    },
    {
      "username": "shuaijin",
      "star": "4"
    },
    {
      "username": "nicyzh",
      "star": "5"
    },
    {
      "username": "20653791",
      "star": "5"
    },
    {
      "username": "3715748",
      "star": "4"
    },
    {
      "username": "Dinja",
      "star": "5"
    },
    {
      "username": "65596546",
      "star": "5"
    },
    {
      "username": "57857018",
      "star": "5"
    },
    {
      "username": "2595427",
      "star": "3"
    },
    {
      "username": "be-my-mirror",
      "star": "4"
    },
    {
      "username": "102844652",
      "star": "5"
    },
    {
      "username": "51586911",
      "star": "4"
    },
    {
      "username": "50609677",
      "star": "4"
    },
    {
      "username": "75455116",
      "star": "4"
    },
    {
      "username": "justone.he",
      "star": "4"
    },
    {
      "username": "1175204",
      "star": "4"
    },
    {
      "username": "angelakristin",
      "star": "4"
    },
    {
      "username": "1328733",
      "star": "4"
    },
    {
      "username": "jojo198271",
      "star": "4"
    },
    {
      "username": "fukai",
      "star": "4"
    },
    {
      "username": "1461901",
      "star": "5"
    },
    {
      "username": "mana",
      "star": "3"
    },
    {
      "username": "Jason_kiss",
      "star": "5"
    },
    {
      "username": "vcbear",
      "star": "5"
    },
    {
      "username": "carrie8",
      "star": "5"
    },
    {
      "username": "dabianju",
      "star": "5"
    },
    {
      "username": "elyn5234",
      "star": "5"
    },
    {
      "username": "ohmyboy",
      "star": "4"
    },
    {
      "username": "CANDYRD",
      "star": 0
    },
    {
      "username": "lnc77",
      "star": 0
    },
    {
      "username": "bianca21",
      "star": "5"
    },
    {
      "username": "2155432",
      "star": "3"
    },
    {
      "username": "3518183",
      "star": "5"
    },
    {
      "username": "taoy",
      "star": "5"
    },
    {
      "username": "2301425",
      "star": "3"
    },
    {
      "username": "2313797",
      "star": "4"
    },
    {
      "username": "3872704",
      "star": "4"
    },
    {
      "username": "celiaking",
      "star": "5"
    },
    {
      "username": "1664137",
      "star": "5"
    },
    {
      "username": "frolasue",
      "star": "4"
    },
    {
      "username": "53255422",
      "star": "5"
    },
    {
      "username": "jessical",
      "star": "5"
    },
    {
      "username": "2813940",
      "star": "5"
    },
    {
      "username": "35608196",
      "star": "4"
    },
    {
      "username": "shawtonli",
      "star": "4"
    },
    {
      "username": "Le0",
      "star": "5"
    },
    {
      "username": "2244688",
      "star": "3"
    },
    {
      "username": "1395324",
      "star": "5"
    },
    {
      "username": "jiuyueyaxiao",
      "star": "5"
    },
    {
      "username": "1140617",
      "star": 0
    },
    {
      "username": "aoke",
      "star": "5"
    },
    {
      "username": "xiaoyilin",
      "star": "5"
    },
    {
      "username": "2551604",
      "star": "4"
    },
    {
      "username": "4418518",
      "star": "4"
    },
    {
      "username": "douban.qiqi",
      "star": "5"
    },
    {
      "username": "4437883",
      "star": "5"
    },
    {
      "username": "sk4ever",
      "star": "5"
    },
    {
      "username": "6328459",
      "star": "5"
    },
    {
      "username": "71049718",
      "star": "4"
    },
    {
      "username": "6328459",
      "star": "5"
    },
    {
      "username": "58471174",
      "star": "3"
    },
    {
      "username": "73666911",
      "star": "5"
    },
    {
      "username": "54614951",
      "star": "5"
    },
    {
      "username": "76851962",
      "star": "4"
    },
    {
      "username": "aibaobaoguai327",
      "star": "5"
    },
    {
      "username": "blueeileency",
      "star": "5"
    },
    {
      "username": "7801839",
      "star": "5"
    },
    {
      "username": "55668756",
      "star": "5"
    },
    {
      "username": "130289224",
      "star": "5"
    },
    {
      "username": "77322988",
      "star": "4"
    },
    {
      "username": "63121383",
      "star": "5"
    },
    {
      "username": "67515390",
      "star": "3"
    },
    {
      "username": "4154402",
      "star": "5"
    },
    {
      "username": "guuuu",
      "star": "5"
    },
    {
      "username": "vincente",
      "star": "5"
    },
    {
      "username": "lemonbaby",
      "star": "5"
    },
    {
      "username": "fuxiu",
      "star": "5"
    },
    {
      "username": "an-sirens",
      "star": "5"
    },
    {
      "username": "julyray",
      "star": "5"
    },
    {
      "username": "alvinlim",
      "star": "5"
    },
    {
      "username": "lilihuidanchu",
      "star": "4"
    },
    {
      "username": "zwtelle",
      "star": "5"
    },
    {
      "username": "shiyueliuri",
      "star": "4"
    },
    {
      "username": "1412024",
      "star": "4"
    },
    {
      "username": "luting_35",
      "star": "4"
    },
    {
      "username": "raykar",
      "star": "5"
    },
    {
      "username": "mimangxiangshui",
      "star": "5"
    },
    {
      "username": "2243197",
      "star": "5"
    },
    {
      "username": "hiruma69",
      "star": "5"
    },
    {
      "username": "xiaokun",
      "star": "3"
    },
    {
      "username": "xiaokun",
      "star": "3"
    },
    {
      "username": "luoan",
      "star": "4"
    },
    {
      "username": "awa126",
      "star": "3"
    },
    {
      "username": "kenshinhyde",
      "star": "4"
    },
    {
      "username": "1183778",
      "star": "5"
    },
    {
      "username": "2655191",
      "star": "5"
    },
    {
      "username": "3854096",
      "star": "5"
    },
    {
      "username": "4372622",
      "star": "4"
    },
    {
      "username": "3028527",
      "star": "5"
    },
    {
      "username": "sanbobo",
      "star": "5"
    },
    {
      "username": "joanna605",
      "star": "5"
    },
    {
      "username": "shawland",
      "star": "5"
    },
    {
      "username": "4165444",
      "star": "5"
    },
    {
      "username": "4411311",
      "star": "4"
    },
    {
      "username": "3462185",
      "star": "5"
    },
    {
      "username": "petitfroid",
      "star": "5"
    },
    {
      "username": "3626358",
      "star": "5"
    },
    {
      "username": "3868293",
      "star": "5"
    },
    {
      "username": "4159422",
      "star": "5"
    },
    {
      "username": "4127091",
      "star": "4"
    },
    {
      "username": "4173529",
      "star": "5"
    },
    {
      "username": "2597884",
      "star": "4"
    },
    {
      "username": "gonghanmo",
      "star": "5"
    },
    {
      "username": "2544597",
      "star": "3"
    },
    {
      "username": "2019237",
      "star": "5"
    },
    {
      "username": "2721529",
      "star": "3"
    },
    {
      "username": "echosanmao",
      "star": "5"
    },
    {
      "username": "2534937",
      "star": "4"
    },
    {
      "username": "linshang",
      "star": "5"
    },
    {
      "username": "1601140",
      "star": "5"
    },
    {
      "username": "2919040",
      "star": "5"
    },
    {
      "username": "zyf",
      "star": "4"
    },
    {
      "username": "1294527",
      "star": "5"
    },
    {
      "username": "merrygoaround",
      "star": "5"
    },
    {
      "username": "2346244",
      "star": "4"
    },
    {
      "username": "2704316",
      "star": "5"
    },
    {
      "username": "willbrighter",
      "star": "5"
    },
    {
      "username": "2039251",
      "star": 0
    },
    {
      "username": "1383818",
      "star": 0
    },
    {
      "username": "2064262",
      "star": 0
    },
    {
      "username": "2981366",
      "star": "4"
    },
    {
      "username": "Vicky77",
      "star": "5"
    },
    {
      "username": "2322682",
      "star": "5"
    },
    {
      "username": "3527190",
      "star": "5"
    },
    {
      "username": "3447079",
      "star": "5"
    },
    {
      "username": "3383374",
      "star": "5"
    },
    {
      "username": "3558851",
      "star": "5"
    },
    {
      "username": "weishenmo",
      "star": "3"
    },
    {
      "username": "fiona_yang",
      "star": "5"
    },
    {
      "username": "1109195",
      "star": "5"
    },
    {
      "username": "meeelove",
      "star": "5"
    },
    {
      "username": "3907866",
      "star": "5"
    },
    {
      "username": "3441577",
      "star": "4"
    },
    {
      "username": "3438841",
      "star": "5"
    },
    {
      "username": "3611691",
      "star": "4"
    },
    {
      "username": "lazybug",
      "star": "5"
    },
    {
      "username": "estimater",
      "star": "5"
    },
    {
      "username": "sophia0123",
      "star": "3"
    },
    {
      "username": "fonne",
      "star": 0
    },
    {
      "username": "1532340",
      "star": 0
    },
    {
      "username": "ouis",
      "star": "3"
    },
    {
      "username": "3362075",
      "star": "4"
    },
    {
      "username": "olioli2006",
      "star": "5"
    },
    {
      "username": "3414799",
      "star": "3"
    },
    {
      "username": "omihart",
      "star": "5"
    },
    {
      "username": "just.c",
      "star": "5"
    },
    {
      "username": "kkdada",
      "star": "5"
    },
    {
      "username": "3950240",
      "star": "5"
    },
    {
      "username": "liushutings",
      "star": "5"
    },
    {
      "username": "3617789",
      "star": "5"
    },
    {
      "username": "4096657",
      "star": "4"
    },
    {
      "username": "4012754",
      "star": "5"
    },
    {
      "username": "Suzieyiyi",
      "star": "5"
    },
    {
      "username": "4027146",
      "star": "5"
    },
    {
      "username": "ddling",
      "star": "5"
    },
    {
      "username": "3929769",
      "star": "5"
    },
    {
      "username": "3991474",
      "star": "5"
    },
    {
      "username": "4105244",
      "star": "4"
    },
    {
      "username": "rachel1399",
      "star": "5"
    },
    {
      "username": "zuzu10",
      "star": "5"
    },
    {
      "username": "27560441",
      "star": "5"
    },
    {
      "username": "4096536",
      "star": "5"
    },
    {
      "username": "terrenchuk",
      "star": "3"
    },
    {
      "username": "Iris-tectorum",
      "star": "5"
    },
    {
      "username": "vitaisachild",
      "star": "4"
    },
    {
      "username": "35212314",
      "star": "5"
    },
    {
      "username": "kasaier",
      "star": "4"
    },
    {
      "username": "10250383",
      "star": "5"
    },
    {
      "username": "jiazi0923",
      "star": "4"
    },
    {
      "username": "cicimint",
      "star": "5"
    },
    {
      "username": "4507523",
      "star": "4"
    },
    {
      "username": "33912527",
      "star": "4"
    },
    {
      "username": "3761305",
      "star": "5"
    },
    {
      "username": "Sirensocier",
      "star": "5"
    },
    {
      "username": "19337266",
      "star": "5"
    },
    {
      "username": "32659611",
      "star": "4"
    },
    {
      "username": "liyifei1105",
      "star": "3"
    },
    {
      "username": "jesuslove",
      "star": "4"
    },
    {
      "username": "2163002",
      "star": "4"
    },
    {
      "username": "wind714",
      "star": 0
    },
    {
      "username": "27864308",
      "star": "5"
    },
    {
      "username": "20070854",
      "star": "5"
    },
    {
      "username": "29051009",
      "star": "5"
    },
    {
      "username": "karine1990",
      "star": "4"
    },
    {
      "username": "bloomy",
      "star": "5"
    },
    {
      "username": "38255442",
      "star": "5"
    },
    {
      "username": "46151279",
      "star": "5"
    },
    {
      "username": "33864966",
      "star": "5"
    },
    {
      "username": "thetraveler",
      "star": "4"
    },
    {
      "username": "30981684",
      "star": "4"
    },
    {
      "username": "45162386",
      "star": "5"
    },
    {
      "username": "35812910",
      "star": "5"
    },
    {
      "username": "44993685",
      "star": "4"
    },
    {
      "username": "jillyyt",
      "star": "3"
    },
    {
      "username": "44566227",
      "star": "5"
    },
    {
      "username": "44556582",
      "star": "5"
    },
    {
      "username": "43861772",
      "star": "5"
    },
    {
      "username": "ro7ss",
      "star": "5"
    },
    {
      "username": "redangel",
      "star": "5"
    },
    {
      "username": "xiaoxiaoyumiko",
      "star": "5"
    },
    {
      "username": "43368020",
      "star": "5"
    },
    {
      "username": "3152514",
      "star": "5"
    },
    {
      "username": "22900885",
      "star": "4"
    },
    {
      "username": "36995354",
      "star": "4"
    },
    {
      "username": "49505674",
      "star": "5"
    },
    {
      "username": "53691936",
      "star": "5"
    },
    {
      "username": "59129484",
      "star": "5"
    },
    {
      "username": "33757163",
      "star": "5"
    },
    {
      "username": "62503908",
      "star": "4"
    },
    {
      "username": "zoesunshine",
      "star": "4"
    },
    {
      "username": "60824284",
      "star": "5"
    },
    {
      "username": "62102177",
      "star": "4"
    },
    {
      "username": "61961796",
      "star": "5"
    },
    {
      "username": "54691318",
      "star": "5"
    },
    {
      "username": "52675855",
      "star": "4"
    },
    {
      "username": "56739632",
      "star": "5"
    },
    {
      "username": "61373542",
      "star": "4"
    },
    {
      "username": "22335129",
      "star": "3"
    },
    {
      "username": "61494069",
      "star": "4"
    },
    {
      "username": "35608196",
      "star": "4"
    },
    {
      "username": "51026799",
      "star": "5"
    },
    {
      "username": "carblse1028",
      "star": "4"
    },
    {
      "username": "60194523",
      "star": "5"
    },
    {
      "username": "55275227",
      "star": "4"
    },
    {
      "username": "chloe1108",
      "star": "5"
    },
    {
      "username": "LauFun",
      "star": "4"
    },
    {
      "username": "44735067",
      "star": "5"
    },
    {
      "username": "1804818",
      "star": "5"
    },
    {
      "username": "eefee",
      "star": "5"
    },
    {
      "username": "59799092",
      "star": "3"
    },
    {
      "username": "46766450",
      "star": "5"
    },
    {
      "username": "57955082",
      "star": "3"
    },
    {
      "username": "59458047",
      "star": "4"
    },
    {
      "username": "50092908",
      "star": "4"
    },
    {
      "username": "55480886",
      "star": "4"
    },
    {
      "username": "58885565",
      "star": "5"
    },
    {
      "username": "15228262",
      "star": "5"
    },
    {
      "username": "51807867",
      "star": "4"
    },
    {
      "username": "47486971",
      "star": "4"
    },
    {
      "username": "CamilleChang",
      "star": "5"
    },
    {
      "username": "gothicmilk",
      "star": "4"
    },
    {
      "username": "49234584",
      "star": "4"
    },
    {
      "username": "58142127",
      "star": "5"
    },
    {
      "username": "momoko1024",
      "star": "5"
    },
    {
      "username": "55559748",
      "star": "4"
    },
    {
      "username": "55990207",
      "star": "5"
    },
    {
      "username": "56743353",
      "star": "5"
    },
    {
      "username": "57282253",
      "star": "5"
    },
    {
      "username": "48924562",
      "star": "4"
    },
    {
      "username": "aesthete",
      "star": "5"
    },
    {
      "username": "47752656",
      "star": "5"
    },
    {
      "username": "congshuli",
      "star": "5"
    },
    {
      "username": "7795838",
      "star": "5"
    },
    {
      "username": "lifeisjourney",
      "star": "4"
    },
    {
      "username": "45258395",
      "star": "5"
    },
    {
      "username": "55447779",
      "star": "5"
    },
    {
      "username": "reliefman",
      "star": "5"
    },
    {
      "username": "15485620",
      "star": "5"
    },
    {
      "username": "53974996",
      "star": "5"
    },
    {
      "username": "54932716",
      "star": 0
    },
    {
      "username": "Rachelssssss",
      "star": "5"
    },
    {
      "username": "bamboonie",
      "star": "4"
    },
    {
      "username": "54416601",
      "star": "5"
    },
    {
      "username": "54553223",
      "star": "5"
    },
    {
      "username": "qingtongkuihua",
      "star": "4"
    },
    {
      "username": "48644510",
      "star": "5"
    },
    {
      "username": "hushabyy",
      "star": "5"
    },
    {
      "username": "13746638",
      "star": "5"
    },
    {
      "username": "50620996",
      "star": "5"
    },
    {
      "username": "53394465",
      "star": "4"
    },
    {
      "username": "sicheung",
      "star": "5"
    },
    {
      "username": "53313739",
      "star": "4"
    },
    {
      "username": "chairmannirvana",
      "star": "4"
    },
    {
      "username": "doublelovediguo",
      "star": "4"
    },
    {
      "username": "51791015",
      "star": "3"
    },
    {
      "username": "53064791",
      "star": "3"
    },
    {
      "username": "32375044",
      "star": "4"
    },
    {
      "username": "52956534",
      "star": "5"
    },
    {
      "username": "treestwins",
      "star": "4"
    },
    {
      "username": "windydai",
      "star": "5"
    },
    {
      "username": "52499804",
      "star": "4"
    },
    {
      "username": "catsaythat",
      "star": "5"
    },
    {
      "username": "poppyxh",
      "star": "5"
    },
    {
      "username": "3242398",
      "star": "4"
    },
    {
      "username": "CreamBaoBao",
      "star": "4"
    },
    {
      "username": "vicsweet",
      "star": "5"
    },
    {
      "username": "missmmmmmm",
      "star": "5"
    },
    {
      "username": "38929467",
      "star": "4"
    },
    {
      "username": "summertune",
      "star": "4"
    },
    {
      "username": "38204564",
      "star": "5"
    },
    {
      "username": "2658254",
      "star": "4"
    },
    {
      "username": "sissiwowo",
      "star": "5"
    },
    {
      "username": "zeizii",
      "star": "5"
    },
    {
      "username": "39301105",
      "star": "5"
    },
    {
      "username": "4063711",
      "star": "4"
    },
    {
      "username": "tangwj886",
      "star": "5"
    },
    {
      "username": "4099970",
      "star": "4"
    },
    {
      "username": "38672809",
      "star": "5"
    },
    {
      "username": "38672809",
      "star": "5"
    },
    {
      "username": "samantha-jy",
      "star": "3"
    },
    {
      "username": "36265929",
      "star": "4"
    },
    {
      "username": "hyto",
      "star": "5"
    },
    {
      "username": "37058993",
      "star": "5"
    },
    {
      "username": "51941719",
      "star": "5"
    },
    {
      "username": "28608533",
      "star": "5"
    },
    {
      "username": "39681873",
      "star": "5"
    },
    {
      "username": "senline",
      "star": "5"
    },
    {
      "username": "senline",
      "star": "4"
    },
    {
      "username": "paimmoke",
      "star": "4"
    },
    {
      "username": "49678307",
      "star": "4"
    },
    {
      "username": "49891008",
      "star": "5"
    },
    {
      "username": "49957383",
      "star": "5"
    },
    {
      "username": "52014042",
      "star": "5"
    },
    {
      "username": "ling01520",
      "star": "5"
    },
    {
      "username": "50892324",
      "star": "4"
    },
    {
      "username": "guizhidaodaan",
      "star": "5"
    },
    {
      "username": "47421357",
      "star": "5"
    },
    {
      "username": "gq0615",
      "star": "4"
    },
    {
      "username": "1646760",
      "star": "4"
    },
    {
      "username": "47087896",
      "star": 0
    },
    {
      "username": "49628023",
      "star": "5"
    },
    {
      "username": "43619981",
      "star": "4"
    },
    {
      "username": "miaomimi313",
      "star": "3"
    },
    {
      "username": "48407590",
      "star": "4"
    },
    {
      "username": "chw217",
      "star": "5"
    },
    {
      "username": "4063952",
      "star": "4"
    },
    {
      "username": "47350198",
      "star": "5"
    },
    {
      "username": "46148262",
      "star": "5"
    },
    {
      "username": "37917676",
      "star": "5"
    },
    {
      "username": "41613915",
      "star": "4"
    },
    {
      "username": "morly",
      "star": "5"
    },
    {
      "username": "58215940",
      "star": "5"
    },
    {
      "username": "65256446",
      "star": "4"
    },
    {
      "username": "56272150",
      "star": "4"
    },
    {
      "username": "48996856",
      "star": "4"
    },
    {
      "username": "greatchaos",
      "star": "5"
    },
    {
      "username": "44904814",
      "star": "5"
    },
    {
      "username": "58952237",
      "star": "4"
    },
    {
      "username": "smallcatkiti",
      "star": "5"
    },
    {
      "username": "62312272",
      "star": "4"
    },
    {
      "username": "57785128",
      "star": "4"
    },
    {
      "username": "62564042",
      "star": "5"
    },
    {
      "username": "2272633",
      "star": "5"
    },
    {
      "username": "58148132",
      "star": "5"
    },
    {
      "username": "40075390",
      "star": "5"
    },
    {
      "username": "49385118",
      "star": "5"
    },
    {
      "username": "touya0229",
      "star": "4"
    },
    {
      "username": "dkx0928",
      "star": "5"
    },
    {
      "username": "francis_xj",
      "star": "5"
    },
    {
      "username": "cancerlies",
      "star": "3"
    },
    {
      "username": "49253343",
      "star": "5"
    },
    {
      "username": "tuanhuibao",
      "star": "5"
    },
    {
      "username": "39005510",
      "star": "4"
    },
    {
      "username": "4091633",
      "star": "5"
    },
    {
      "username": "44744970",
      "star": "3"
    },
    {
      "username": "47615130",
      "star": "5"
    },
    {
      "username": "linduoduo",
      "star": "5"
    },
    {
      "username": "Hgou2",
      "star": "5"
    },
    {
      "username": "33959216",
      "star": "5"
    },
    {
      "username": "40793114",
      "star": "5"
    },
    {
      "username": "1828278",
      "star": "5"
    },
    {
      "username": "27633770",
      "star": "5"
    },
    {
      "username": "33327961",
      "star": "5"
    },
    {
      "username": "zmhc",
      "star": "5"
    },
    {
      "username": "bloomy",
      "star": "5"
    },
    {
      "username": "dianjinse",
      "star": "5"
    },
    {
      "username": "lianlian725",
      "star": "5"
    },
    {
      "username": "2389613",
      "star": "5"
    },
    {
      "username": "Demolo",
      "star": "5"
    },
    {
      "username": "2703382",
      "star": "4"
    },
    {
      "username": "comin",
      "star": "5"
    },
    {
      "username": "fiona_zff",
      "star": "4"
    },
    {
      "username": "2648168",
      "star": "4"
    },
    {
      "username": "Miss.Mihu",
      "star": "4"
    },
    {
      "username": "2526927",
      "star": "4"
    },
    {
      "username": "gaara_wei",
      "star": "5"
    },
    {
      "username": "shadow9",
      "star": "4"
    },
    {
      "username": "2430889",
      "star": "5"
    },
    {
      "username": "2410680",
      "star": "4"
    },
    {
      "username": "2504521",
      "star": 0
    },
    {
      "username": "Camui.Arashi",
      "star": "4"
    },
    {
      "username": "dongkuichen",
      "star": "4"
    },
    {
      "username": "2326809",
      "star": "5"
    },
    {
      "username": "1612563",
      "star": "4"
    },
    {
      "username": "2450647",
      "star": "5"
    },
    {
      "username": "2412550",
      "star": "4"
    },
    {
      "username": "2314386",
      "star": "5"
    },
    {
      "username": "2314386",
      "star": "5"
    },
    {
      "username": "tatara",
      "star": "5"
    },
    {
      "username": "dangchan",
      "star": "3"
    },
    {
      "username": "2473069",
      "star": "5"
    },
    {
      "username": "talentlaglas",
      "star": "5"
    },
    {
      "username": "maixiaohuang-la",
      "star": "4"
    },
    {
      "username": "alale1983",
      "star": "5"
    },
    {
      "username": "appleciwei",
      "star": "5"
    },
    {
      "username": "axjlbbt",
      "star": "5"
    },
    {
      "username": "2311554",
      "star": "4"
    },
    {
      "username": "2946943",
      "star": "4"
    },
    {
      "username": "shizhuofeng",
      "star": "5"
    },
    {
      "username": "1916735",
      "star": "4"
    },
    {
      "username": "pupil0725",
      "star": "5"
    },
    {
      "username": "sunnykz",
      "star": "5"
    },
    {
      "username": "2526800",
      "star": "3"
    },
    {
      "username": "3071014",
      "star": "4"
    },
    {
      "username": "hanalee1897",
      "star": "5"
    },
    {
      "username": "3348427",
      "star": "3"
    },
    {
      "username": "xiaoxutuantuan",
      "star": "5"
    },
    {
      "username": "4658773",
      "star": "5"
    },
    {
      "username": "2568304",
      "star": "5"
    },
    {
      "username": "5263653",
      "star": "5"
    },
    {
      "username": "5951373",
      "star": "5"
    },
    {
      "username": "yy46523793",
      "star": "2"
    },
    {
      "username": "4186249",
      "star": "5"
    },
    {
      "username": "Backtears",
      "star": "4"
    },
    {
      "username": "valewang",
      "star": "5"
    },
    {
      "username": "luxifero",
      "star": "4"
    },
    {
      "username": "lynmn",
      "star": "4"
    },
    {
      "username": "1602643",
      "star": "5"
    },
    {
      "username": "4630603",
      "star": 0
    },
    {
      "username": "xiaoxiaolaotou",
      "star": 0
    },
    {
      "username": "wjjjzz",
      "star": "5"
    },
    {
      "username": "4571275",
      "star": "4"
    },
    {
      "username": "peterkid",
      "star": "5"
    },
    {
      "username": "yujianni",
      "star": "4"
    },
    {
      "username": "4134944",
      "star": "5"
    },
    {
      "username": "4509061",
      "star": "5"
    },
    {
      "username": "4490350",
      "star": "3"
    },
    {
      "username": "3132239",
      "star": "5"
    },
    {
      "username": "2294148",
      "star": "5"
    },
    {
      "username": "4451695",
      "star": "5"
    },
    {
      "username": "2565589",
      "star": "4"
    },
    {
      "username": "28406683",
      "star": "4"
    },
    {
      "username": "mouzhu",
      "star": "5"
    },
    {
      "username": "20892121",
      "star": "4"
    },
    {
      "username": "2313256",
      "star": "5"
    },
    {
      "username": "wwyoshiki",
      "star": "5"
    },
    {
      "username": "18523904",
      "star": "4"
    },
    {
      "username": "17247794",
      "star": "4"
    },
    {
      "username": "14863164",
      "star": "3"
    },
    {
      "username": "3565476",
      "star": 0
    },
    {
      "username": "4093713",
      "star": "5"
    },
    {
      "username": "15014404",
      "star": "5"
    },
    {
      "username": "cocowool",
      "star": "4"
    },
    {
      "username": "13831882",
      "star": "5"
    },
    {
      "username": "4582066",
      "star": "5"
    },
    {
      "username": "miaoshu922",
      "star": "5"
    },
    {
      "username": "4525377",
      "star": "5"
    },
    {
      "username": "solon4ever",
      "star": "5"
    },
    {
      "username": "9080224",
      "star": "5"
    },
    {
      "username": "3197634",
      "star": "5"
    },
    {
      "username": "4905678",
      "star": "4"
    },
    {
      "username": "datou146",
      "star": "5"
    },
    {
      "username": "89021640",
      "star": "5"
    },
    {
      "username": "89021640",
      "star": "5"
    },
    {
      "username": "52000938",
      "star": "4"
    },
    {
      "username": "aprilchild",
      "star": "2"
    },
    {
      "username": "67220293",
      "star": "4"
    },
    {
      "username": "beigi",
      "star": "4"
    },
    {
      "username": "2591073",
      "star": "4"
    },
    {
      "username": "spicycandy",
      "star": 0
    },
    {
      "username": "2776337",
      "star": "4"
    },
    {
      "username": "mystory",
      "star": "4"
    },
    {
      "username": "1559700",
      "star": "5"
    },
    {
      "username": "1849986",
      "star": "4"
    },
    {
      "username": "gogo530",
      "star": "5"
    },
    {
      "username": "1887298",
      "star": "5"
    },
    {
      "username": "ciccyzcy",
      "star": "5"
    },
    {
      "username": "sixseveneight",
      "star": "4"
    },
    {
      "username": "1882286",
      "star": "5"
    },
    {
      "username": "ginhl",
      "star": "5"
    },
    {
      "username": "2100629",
      "star": "5"
    },
    {
      "username": "zhao_yunyi",
      "star": "4"
    },
    {
      "username": "1993672",
      "star": "5"
    },
    {
      "username": "2056888",
      "star": "4"
    },
    {
      "username": "4230062",
      "star": "4"
    },
    {
      "username": "4303809",
      "star": "3"
    },
    {
      "username": "4285701",
      "star": "5"
    },
    {
      "username": "hanssen",
      "star": "4"
    },
    {
      "username": "4291975",
      "star": "4"
    },
    {
      "username": "ermu",
      "star": 0
    },
    {
      "username": "4279879",
      "star": "5"
    },
    {
      "username": "1758262",
      "star": "5"
    },
    {
      "username": "1413809",
      "star": "4"
    },
    {
      "username": "xiaolinzijoy",
      "star": "5"
    },
    {
      "username": "xiongmaofuren",
      "star": "4"
    },
    {
      "username": "1458707",
      "star": "4"
    },
    {
      "username": "2316325",
      "star": "4"
    },
    {
      "username": "4166923",
      "star": "5"
    },
    {
      "username": "2855900",
      "star": "5"
    },
    {
      "username": "1508688",
      "star": "5"
    },
    {
      "username": "Bugman",
      "star": "4"
    },
    {
      "username": "1381577",
      "star": "5"
    },
    {
      "username": "irockthebest",
      "star": "5"
    },
    {
      "username": "1398862",
      "star": "5"
    },
    {
      "username": "hxj910",
      "star": "4"
    },
    {
      "username": "debbieyoung",
      "star": "5"
    },
    {
      "username": "1413725",
      "star": "5"
    },
    {
      "username": "3075486",
      "star": "5"
    },
    {
      "username": "3314222",
      "star": "3"
    },
    {
      "username": "3346224",
      "star": "5"
    },
    {
      "username": "2218750",
      "star": "4"
    },
    {
      "username": "3587259",
      "star": "4"
    },
    {
      "username": "qian.zhang",
      "star": "5"
    },
    {
      "username": "3608628",
      "star": "4"
    },
    {
      "username": "3435687",
      "star": "5"
    },
    {
      "username": "xinnuo6068",
      "star": "4"
    },
    {
      "username": "2783787",
      "star": "4"
    },
    {
      "username": "3533625",
      "star": "5"
    },
    {
      "username": "3445742",
      "star": "4"
    },
    {
      "username": "jiebaby",
      "star": "4"
    },
    {
      "username": "3235385",
      "star": "3"
    },
    {
      "username": "3591962",
      "star": "4"
    },
    {
      "username": "2636194",
      "star": "5"
    },
    {
      "username": "linfarfar",
      "star": "4"
    },
    {
      "username": "leuchtturm",
      "star": "5"
    },
    {
      "username": "peach.M.yj.W",
      "star": "5"
    },
    {
      "username": "helenforce",
      "star": "5"
    },
    {
      "username": "1225415",
      "star": "4"
    },
    {
      "username": "1814946",
      "star": "4"
    },
    {
      "username": "1522627",
      "star": 0
    },
    {
      "username": "1450539",
      "star": "5"
    },
    {
      "username": "janelifan",
      "star": "4"
    },
    {
      "username": "nnw809",
      "star": "3"
    },
    {
      "username": "sereinrock",
      "star": "5"
    },
    {
      "username": "angleine",
      "star": "5"
    },
    {
      "username": "castor_pollux",
      "star": "5"
    },
    {
      "username": "duixi",
      "star": "3"
    },
    {
      "username": "sunnybaby727",
      "star": "4"
    },
    {
      "username": "3000258",
      "star": "4"
    },
    {
      "username": "3022214",
      "star": "5"
    },
    {
      "username": "2118569",
      "star": "5"
    },
    {
      "username": "2219781",
      "star": "4"
    },
    {
      "username": "2045954",
      "star": "5"
    },
    {
      "username": "2228888",
      "star": "4"
    },
    {
      "username": "lucine.zhang",
      "star": "5"
    },
    {
      "username": "1907333",
      "star": "5"
    },
    {
      "username": "2258633",
      "star": "5"
    },
    {
      "username": "cathyhu",
      "star": "5"
    },
    {
      "username": "prate",
      "star": "5"
    },
    {
      "username": "cahyi",
      "star": "5"
    },
    {
      "username": "1215042",
      "star": "4"
    },
    {
      "username": "smalleye",
      "star": "5"
    },
    {
      "username": "rakbumps",
      "star": "4"
    },
    {
      "username": "jj26",
      "star": "5"
    },
    {
      "username": "bosk",
      "star": "4"
    },
    {
      "username": "3398026",
      "star": "5"
    },
    {
      "username": "cherrrrrry",
      "star": "4"
    },
    {
      "username": "Uni_zz",
      "star": "5"
    },
    {
      "username": "kleinesonne",
      "star": "4"
    },
    {
      "username": "magicwuji",
      "star": "4"
    },
    {
      "username": "yaqing",
      "star": "4"
    },
    {
      "username": "54413726",
      "star": "4"
    },
    {
      "username": "46645966",
      "star": "3"
    },
    {
      "username": "62973237",
      "star": "4"
    },
    {
      "username": "64511095",
      "star": "5"
    },
    {
      "username": "myi2318",
      "star": "5"
    },
    {
      "username": "OrangeXia",
      "star": "5"
    },
    {
      "username": "47201465",
      "star": "5"
    },
    {
      "username": "69606564",
      "star": "5"
    },
    {
      "username": "rebacca_frompz",
      "star": 0
    },
    {
      "username": "54852182",
      "star": "5"
    },
    {
      "username": "69278785",
      "star": "4"
    },
    {
      "username": "tanbupofengqing",
      "star": "5"
    },
    {
      "username": "tanbupofengqing",
      "star": "5"
    },
    {
      "username": "tanbupofengqing",
      "star": "5"
    },
    {
      "username": "47872412",
      "star": "5"
    },
    {
      "username": "52259960",
      "star": "5"
    },
    {
      "username": "43553321",
      "star": "5"
    },
    {
      "username": "58001871",
      "star": "4"
    },
    {
      "username": "49037310",
      "star": "5"
    },
    {
      "username": "62451275",
      "star": "4"
    },
    {
      "username": "chero007",
      "star": "4"
    },
    {
      "username": "secondidentity",
      "star": "5"
    },
    {
      "username": "48968585",
      "star": "5"
    },
    {
      "username": "49149424",
      "star": "4"
    },
    {
      "username": "1268050",
      "star": "5"
    },
    {
      "username": "CyberKnight",
      "star": "4"
    },
    {
      "username": "veryhilda",
      "star": "5"
    },
    {
      "username": "at_summer",
      "star": "3"
    },
    {
      "username": "80742360",
      "star": "5"
    },
    {
      "username": "57598837",
      "star": "4"
    },
    {
      "username": "73178813",
      "star": "4"
    },
    {
      "username": "muyeandmuy",
      "star": "5"
    },
    {
      "username": "66653490",
      "star": "5"
    },
    {
      "username": "4362946",
      "star": "4"
    },
    {
      "username": "80209529",
      "star": "5"
    },
    {
      "username": "68508604",
      "star": "5"
    },
    {
      "username": "61738495",
      "star": "5"
    },
    {
      "username": "79715908",
      "star": "5"
    },
    {
      "username": "74228591",
      "star": "4"
    },
    {
      "username": "67220568",
      "star": "5"
    },
    {
      "username": "68240434",
      "star": "4"
    },
    {
      "username": "belyone",
      "star": "5"
    },
    {
      "username": "72286510",
      "star": "5"
    },
    {
      "username": "85360872",
      "star": "4"
    },
    {
      "username": "86211380",
      "star": "5"
    },
    {
      "username": "jackieyang0101",
      "star": "5"
    },
    {
      "username": "87659176",
      "star": "5"
    },
    {
      "username": "mrzeng1993",
      "star": "3"
    },
    {
      "username": "64236786",
      "star": "5"
    },
    {
      "username": "51132276",
      "star": "2"
    },
    {
      "username": "melanthaforever",
      "star": "4"
    },
    {
      "username": "dp931023",
      "star": "5"
    },
    {
      "username": "dp931023",
      "star": "5"
    },
    {
      "username": "jieyongdie",
      "star": "5"
    },
    {
      "username": "54822545",
      "star": "3"
    },
    {
      "username": "66815220",
      "star": "4"
    },
    {
      "username": "75216540",
      "star": "4"
    },
    {
      "username": "75182850",
      "star": "4"
    },
    {
      "username": "71740215",
      "star": "4"
    },
    {
      "username": "50632389",
      "star": "4"
    },
    {
      "username": "45209996",
      "star": "4"
    },
    {
      "username": "Ah-haha",
      "star": "5"
    },
    {
      "username": "119698821",
      "star": "3"
    },
    {
      "username": "68665213",
      "star": "5"
    },
    {
      "username": "98469295",
      "star": "4"
    },
    {
      "username": "115224113",
      "star": "5"
    },
    {
      "username": "110172016",
      "star": "5"
    },
    {
      "username": "81721687",
      "star": "4"
    },
    {
      "username": "Mov1e-Clan",
      "star": "4"
    },
    {
      "username": "hermione_lv",
      "star": "3"
    },
    {
      "username": "76023924",
      "star": "4"
    },
    {
      "username": "67623924",
      "star": "5"
    },
    {
      "username": "61943440",
      "star": "5"
    },
    {
      "username": "66627204",
      "star": "5"
    },
    {
      "username": "52497934",
      "star": "4"
    },
    {
      "username": "xyc1987",
      "star": "5"
    },
    {
      "username": "xyc1987",
      "star": "5"
    },
    {
      "username": "68585386",
      "star": "4"
    },
    {
      "username": "61873687",
      "star": "5"
    },
    {
      "username": "121549348",
      "star": "5"
    },
    {
      "username": "75987824",
      "star": "4"
    },
    {
      "username": "53507373",
      "star": "5"
    },
    {
      "username": "83119722",
      "star": "4"
    },
    {
      "username": "canson",
      "star": "4"
    },
    {
      "username": "shirleysyb",
      "star": "5"
    },
    {
      "username": "crow.",
      "star": "5"
    },
    {
      "username": "strawberryever",
      "star": "5"
    },
    {
      "username": "danniwu",
      "star": "5"
    },
    {
      "username": "echogo",
      "star": "2"
    },
    {
      "username": "34363043",
      "star": "5"
    },
    {
      "username": "ga880316",
      "star": "4"
    },
    {
      "username": "divingsun",
      "star": "4"
    },
    {
      "username": "yanrunze",
      "star": "5"
    },
    {
      "username": "4513540",
      "star": "4"
    },
    {
      "username": "47701435",
      "star": "5"
    },
    {
      "username": "3875163",
      "star": "3"
    },
    {
      "username": "4490135",
      "star": "2"
    },
    {
      "username": "bbbbb",
      "star": "4"
    },
    {
      "username": "Robert",
      "star": "3"
    },
    {
      "username": "1001453",
      "star": "4"
    },
    {
      "username": "jay.ziheng",
      "star": "5"
    },
    {
      "username": "2872922",
      "star": "5"
    },
    {
      "username": "2483388",
      "star": "2"
    },
    {
      "username": "1026789",
      "star": "3"
    },
    {
      "username": "34193886",
      "star": "4"
    },
    {
      "username": "diaddra",
      "star": "5"
    },
    {
      "username": "mufei",
      "star": 0
    },
    {
      "username": "1071810",
      "star": 0
    },
    {
      "username": "yshhq",
      "star": 0
    },
    {
      "username": "helen_su",
      "star": "5"
    },
    {
      "username": "1000446",
      "star": "4"
    },
    {
      "username": "zx001xz111",
      "star": "4"
    },
    {
      "username": "nansheng817",
      "star": "5"
    },
    {
      "username": "anht321",
      "star": "4"
    },
    {
      "username": "zgjie",
      "star": "5"
    },
    {
      "username": "eolande",
      "star": "4"
    },
    {
      "username": "1108097",
      "star": "5"
    },
    {
      "username": "1010899",
      "star": "4"
    },
    {
      "username": "spriner",
      "star": "2"
    },
    {
      "username": "fodo",
      "star": "5"
    },
    {
      "username": "jie",
      "star": "5"
    },
    {
      "username": "downs",
      "star": "5"
    },
    {
      "username": "pandy",
      "star": "5"
    },
    {
      "username": "Sueyan",
      "star": "5"
    },
    {
      "username": "weedself",
      "star": "4"
    },
    {
      "username": "youning99",
      "star": "5"
    },
    {
      "username": "1118759",
      "star": "5"
    },
    {
      "username": "suneykillbobo",
      "star": "4"
    },
    {
      "username": "1104871",
      "star": "5"
    },
    {
      "username": "2358547",
      "star": "5"
    },
    {
      "username": "v-neverever",
      "star": "5"
    },
    {
      "username": "84353417",
      "star": "5"
    },
    {
      "username": "GIRLLEE",
      "star": "5"
    },
    {
      "username": "1294738",
      "star": "5"
    },
    {
      "username": "doudou520",
      "star": "5"
    },
    {
      "username": "comelate",
      "star": "5"
    },
    {
      "username": "endymion",
      "star": "5"
    },
    {
      "username": "2496878",
      "star": "5"
    },
    {
      "username": "williamyouguess",
      "star": "4"
    },
    {
      "username": "frlazi",
      "star": "5"
    },
    {
      "username": "jijipanda",
      "star": "4"
    },
    {
      "username": "1343189",
      "star": "4"
    },
    {
      "username": "meiyang",
      "star": "5"
    },
    {
      "username": "zhengshuashua",
      "star": "5"
    },
    {
      "username": "nextsecond",
      "star": "5"
    },
    {
      "username": "loveeesc",
      "star": "5"
    },
    {
      "username": "Nancy_y",
      "star": "5"
    },
    {
      "username": "meadjohnson",
      "star": "5"
    },
    {
      "username": "bensusanlana",
      "star": "5"
    },
    {
      "username": "2213304",
      "star": "3"
    },
    {
      "username": "63959069",
      "star": "4"
    },
    {
      "username": "1033023",
      "star": "5"
    },
    {
      "username": "kashiata",
      "star": "5"
    },
    {
      "username": "2024853",
      "star": "5"
    },
    {
      "username": "32817761",
      "star": "4"
    },
    {
      "username": "ninecats",
      "star": "5"
    },
    {
      "username": "gelk",
      "star": "5"
    },
    {
      "username": "mdya",
      "star": "5"
    },
    {
      "username": "feinlin",
      "star": "5"
    },
    {
      "username": "1642662",
      "star": "5"
    },
    {
      "username": "2852096",
      "star": "5"
    },
    {
      "username": "2647085",
      "star": "4"
    },
    {
      "username": "22456771",
      "star": "5"
    },
    {
      "username": "myxiaoxiao",
      "star": "5"
    },
    {
      "username": "yizilee0715",
      "star": "5"
    },
    {
      "username": "tomcruiseyy",
      "star": "5"
    },
    {
      "username": "yuliamelody",
      "star": "4"
    },
    {
      "username": "jackieli",
      "star": "5"
    },
    {
      "username": "sunnychou",
      "star": "5"
    },
    {
      "username": "Raoul",
      "star": "5"
    },
    {
      "username": "2224689",
      "star": "5"
    },
    {
      "username": "zhaoyajing",
      "star": "5"
    },
    {
      "username": "tallrain",
      "star": "5"
    },
    {
      "username": "babybiscuits",
      "star": "5"
    },
    {
      "username": "Losersclub1958",
      "star": "5"
    },
    {
      "username": "stonejacket",
      "star": "5"
    },
    {
      "username": "immortal_3",
      "star": "4"
    },
    {
      "username": "anywaylu",
      "star": "5"
    },
    {
      "username": "45283051",
      "star": "5"
    },
    {
      "username": "58324593",
      "star": "3"
    },
    {
      "username": "62476051",
      "star": "5"
    },
    {
      "username": "44338354",
      "star": "5"
    },
    {
      "username": "r9ronaldo",
      "star": "5"
    },
    {
      "username": "Emily_ma",
      "star": "4"
    },
    {
      "username": "zbccy",
      "star": "5"
    },
    {
      "username": "1844482",
      "star": "4"
    },
    {
      "username": "kikisyoke",
      "star": "5"
    },
    {
      "username": "1243863",
      "star": "4"
    },
    {
      "username": "fengxifengxi",
      "star": "5"
    },
    {
      "username": "58404621",
      "star": "5"
    },
    {
      "username": "fumika0707",
      "star": "4"
    },
    {
      "username": "38275241",
      "star": "5"
    },
    {
      "username": "RLienhzg",
      "star": "4"
    },
    {
      "username": "catcissy",
      "star": "4"
    },
    {
      "username": "xiaoker",
      "star": "5"
    },
    {
      "username": "zhudouhaipa",
      "star": "4"
    },
    {
      "username": "lady...",
      "star": "4"
    },
    {
      "username": "39470765",
      "star": "5"
    },
    {
      "username": "woyouduohenni",
      "star": "5"
    },
    {
      "username": "sabretooth",
      "star": "4"
    },
    {
      "username": "1576678",
      "star": "5"
    },
    {
      "username": "motu",
      "star": "5"
    },
    {
      "username": "41589260",
      "star": "5"
    },
    {
      "username": "2471629",
      "star": "5"
    },
    {
      "username": "73139452",
      "star": "5"
    },
    {
      "username": "42540115",
      "star": "5"
    },
    {
      "username": "pulporange",
      "star": "3"
    },
    {
      "username": "catyofgarden",
      "star": "4"
    },
    {
      "username": "billbiao",
      "star": 0
    },
    {
      "username": "fishgirlsong",
      "star": "3"
    },
    {
      "username": "liushusheng",
      "star": "4"
    },
    {
      "username": "alic",
      "star": "4"
    },
    {
      "username": "cathytuski",
      "star": "4"
    },
    {
      "username": "ihonghong",
      "star": "5"
    },
    {
      "username": "franceslei",
      "star": "5"
    },
    {
      "username": "zhanye040218",
      "star": "5"
    },
    {
      "username": "cannycjy",
      "star": "5"
    },
    {
      "username": "gongdeguang",
      "star": "5"
    },
    {
      "username": "1625316",
      "star": "4"
    },
    {
      "username": "eillen",
      "star": "4"
    },
    {
      "username": "ariazhuzi",
      "star": "5"
    },
    {
      "username": "Nydemon",
      "star": "5"
    },
    {
      "username": "jadeAA",
      "star": "4"
    },
    {
      "username": "25516959",
      "star": "4"
    },
    {
      "username": "68795891",
      "star": "5"
    },
    {
      "username": "tianshangkuaile",
      "star": "4"
    },
    {
      "username": "3595385",
      "star": "5"
    },
    {
      "username": "kevin7363",
      "star": "5"
    },
    {
      "username": "3042073",
      "star": "5"
    },
    {
      "username": "hobbyhorse",
      "star": "4"
    },
    {
      "username": "eabee",
      "star": "4"
    },
    {
      "username": "murongheruo",
      "star": "5"
    },
    {
      "username": "2206174",
      "star": "5"
    },
    {
      "username": "2856059",
      "star": "5"
    },
    {
      "username": "gp",
      "star": "4"
    },
    {
      "username": "msspider",
      "star": "4"
    },
    {
      "username": "coraguo",
      "star": "5"
    },
    {
      "username": "leetingsky",
      "star": "5"
    },
    {
      "username": "46931196",
      "star": "5"
    },
    {
      "username": "axianxian",
      "star": "4"
    },
    {
      "username": "73486060",
      "star": "4"
    },
    {
      "username": "65942697",
      "star": "5"
    },
    {
      "username": "74231366",
      "star": "4"
    },
    {
      "username": "51241284",
      "star": "3"
    },
    {
      "username": "jmmhoney",
      "star": "5"
    },
    {
      "username": "jmmhoney",
      "star": "5"
    },
    {
      "username": "jmmhoney",
      "star": "5"
    },
    {
      "username": "yaowengyan",
      "star": "4"
    },
    {
      "username": "mysalleygarden",
      "star": "5"
    },
    {
      "username": "64948522",
      "star": "5"
    },
    {
      "username": "5266908",
      "star": "3"
    },
    {
      "username": "67311017",
      "star": "5"
    },
    {
      "username": "74864273",
      "star": "5"
    },
    {
      "username": "93159068",
      "star": "5"
    },
    {
      "username": "yun_0320x",
      "star": "4"
    },
    {
      "username": "youhebi",
      "star": "5"
    },
    {
      "username": "Fleetstreet",
      "star": "5"
    },
    {
      "username": "1560967",
      "star": "4"
    },
    {
      "username": "2461873",
      "star": "5"
    },
    {
      "username": "CrystalSummer",
      "star": "5"
    },
    {
      "username": "1823512",
      "star": "5"
    },
    {
      "username": "neverland18",
      "star": "4"
    },
    {
      "username": "ten10",
      "star": "5"
    },
    {
      "username": "ning1119",
      "star": "4"
    },
    {
      "username": "1258126",
      "star": "5"
    },
    {
      "username": "echow",
      "star": "4"
    },
    {
      "username": "3698567",
      "star": "4"
    },
    {
      "username": "2992753",
      "star": "5"
    },
    {
      "username": "shehui",
      "star": 0
    },
    {
      "username": "2789486",
      "star": "5"
    },
    {
      "username": "feifeinanmu",
      "star": "5"
    },
    {
      "username": "seally",
      "star": "4"
    },
    {
      "username": "1838485",
      "star": "4"
    },
    {
      "username": "Lucyz",
      "star": "5"
    },
    {
      "username": "mystove",
      "star": "5"
    },
    {
      "username": "levender",
      "star": "5"
    },
    {
      "username": "jiojio",
      "star": "4"
    },
    {
      "username": "2561889",
      "star": "5"
    },
    {
      "username": "2776345",
      "star": "4"
    },
    {
      "username": "3827786",
      "star": "5"
    },
    {
      "username": "3649719",
      "star": "4"
    },
    {
      "username": "reflection620",
      "star": "4"
    },
    {
      "username": "3421039",
      "star": "5"
    },
    {
      "username": "raincloudsdec",
      "star": "5"
    },
    {
      "username": "4037779",
      "star": "4"
    },
    {
      "username": "3985174",
      "star": "4"
    },
    {
      "username": "bigcherry",
      "star": "3"
    },
    {
      "username": "meixin983",
      "star": "5"
    },
    {
      "username": "3720954",
      "star": "5"
    },
    {
      "username": "8407907",
      "star": "4"
    },
    {
      "username": "34957484",
      "star": "5"
    },
    {
      "username": "34874953",
      "star": "5"
    },
    {
      "username": "25515233",
      "star": "5"
    },
    {
      "username": "29748769",
      "star": "5"
    },
    {
      "username": "fangtian",
      "star": "5"
    },
    {
      "username": "45948941",
      "star": "4"
    },
    {
      "username": "2996338",
      "star": "4"
    },
    {
      "username": "44184190",
      "star": "4"
    },
    {
      "username": "JoeyStephanie",
      "star": "5"
    },
    {
      "username": "tanuki",
      "star": "5"
    },
    {
      "username": "47388400",
      "star": "5"
    },
    {
      "username": "45318200",
      "star": "5"
    },
    {
      "username": "dayong91",
      "star": "5"
    },
    {
      "username": "52401841",
      "star": "5"
    },
    {
      "username": "62829770",
      "star": "3"
    },
    {
      "username": "53509957",
      "star": "4"
    },
    {
      "username": "sakurahl333",
      "star": "5"
    },
    {
      "username": "57977995",
      "star": "4"
    },
    {
      "username": "37586924",
      "star": "5"
    },
    {
      "username": "kakaellen",
      "star": "5"
    },
    {
      "username": "57399032",
      "star": "5"
    },
    {
      "username": "38995374",
      "star": "5"
    },
    {
      "username": "54080937",
      "star": "3"
    },
    {
      "username": "52317966",
      "star": "5"
    },
    {
      "username": "57901096",
      "star": "4"
    },
    {
      "username": "50533885",
      "star": "5"
    },
    {
      "username": "56060084",
      "star": "3"
    },
    {
      "username": "3492933",
      "star": "5"
    },
    {
      "username": "58119815",
      "star": "5"
    },
    {
      "username": "23511966",
      "star": "4"
    },
    {
      "username": "49308438",
      "star": "5"
    },
    {
      "username": "McGail",
      "star": "5"
    },
    {
      "username": "leocess822",
      "star": "5"
    },
    {
      "username": "2302807",
      "star": "4"
    },
    {
      "username": "46156616",
      "star": "5"
    },
    {
      "username": "38672585",
      "star": "4"
    },
    {
      "username": "43750430",
      "star": "3"
    },
    {
      "username": "49447050",
      "star": "5"
    },
    {
      "username": "shixiaojun8",
      "star": "5"
    },
    {
      "username": "52485373",
      "star": "4"
    },
    {
      "username": "41981477",
      "star": "5"
    },
    {
      "username": "41981477",
      "star": "5"
    },
    {
      "username": "50539364",
      "star": "5"
    },
    {
      "username": "48361618",
      "star": "5"
    },
    {
      "username": "2129329",
      "star": "5"
    },
    {
      "username": "51841852",
      "star": "4"
    },
    {
      "username": "53809440",
      "star": "5"
    },
    {
      "username": "38502674",
      "star": "5"
    },
    {
      "username": "1810791",
      "star": "5"
    },
    {
      "username": "53545901",
      "star": "3"
    },
    {
      "username": "48965560",
      "star": "5"
    },
    {
      "username": "53560596",
      "star": "5"
    },
    {
      "username": "loyingme",
      "star": "4"
    },
    {
      "username": "53036012",
      "star": "3"
    },
    {
      "username": "magictqn",
      "star": "5"
    },
    {
      "username": "wenwbingb",
      "star": "4"
    },
    {
      "username": "51743577",
      "star": "4"
    },
    {
      "username": "52731124",
      "star": "3"
    },
    {
      "username": "51980999",
      "star": "5"
    },
    {
      "username": "lynnslove",
      "star": "4"
    },
    {
      "username": "mymonochromecc",
      "star": "5"
    },
    {
      "username": "31811106",
      "star": "5"
    },
    {
      "username": "gaoyiwei",
      "star": "4"
    },
    {
      "username": "3825433",
      "star": "5"
    },
    {
      "username": "ebony_sunshine",
      "star": "5"
    },
    {
      "username": "39482954",
      "star": "5"
    },
    {
      "username": "1422668",
      "star": "5"
    },
    {
      "username": "2736339",
      "star": "5"
    },
    {
      "username": "3200414",
      "star": "3"
    },
    {
      "username": "gynecologist",
      "star": "5"
    },
    {
      "username": "3362230",
      "star": "5"
    },
    {
      "username": "52164483",
      "star": "5"
    },
    {
      "username": "52078014",
      "star": "4"
    },
    {
      "username": "2200773",
      "star": "4"
    },
    {
      "username": "asukaxyt",
      "star": "4"
    },
    {
      "username": "52174237",
      "star": "4"
    },
    {
      "username": "ziyuting",
      "star": "5"
    },
    {
      "username": "3000203",
      "star": "4"
    },
    {
      "username": "48488047",
      "star": "5"
    },
    {
      "username": "sarah8861",
      "star": "5"
    },
    {
      "username": "1722477",
      "star": "3"
    },
    {
      "username": "2220178",
      "star": "5"
    },
    {
      "username": "50442713",
      "star": "4"
    },
    {
      "username": "momoangel",
      "star": "5"
    },
    {
      "username": "loveyamapforeve",
      "star": "4"
    },
    {
      "username": "14621940",
      "star": "4"
    },
    {
      "username": "geniusneal",
      "star": "5"
    },
    {
      "username": "AstridLin",
      "star": "5"
    },
    {
      "username": "66414116",
      "star": "4"
    },
    {
      "username": "victor55",
      "star": "5"
    },
    {
      "username": "66341681",
      "star": "3"
    },
    {
      "username": "43716329",
      "star": "5"
    },
    {
      "username": "65339802",
      "star": "5"
    },
    {
      "username": "63878683",
      "star": "5"
    },
    {
      "username": "57802836",
      "star": "5"
    },
    {
      "username": "64657294",
      "star": "5"
    },
    {
      "username": "64597306",
      "star": "5"
    },
    {
      "username": "64597306",
      "star": "5"
    },
    {
      "username": "50921551",
      "star": "5"
    },
    {
      "username": "62962377",
      "star": "5"
    },
    {
      "username": "acloud",
      "star": "5"
    },
    {
      "username": "54045746",
      "star": "3"
    },
    {
      "username": "iguana07",
      "star": "5"
    },
    {
      "username": "43770781",
      "star": "5"
    },
    {
      "username": "59226534",
      "star": "5"
    },
    {
      "username": "45668305",
      "star": "4"
    },
    {
      "username": "3617313",
      "star": "4"
    },
    {
      "username": "48067555",
      "star": "5"
    },
    {
      "username": "9531257",
      "star": "5"
    },
    {
      "username": "46316226",
      "star": "5"
    },
    {
      "username": "40019708",
      "star": "4"
    },
    {
      "username": "46667065",
      "star": "4"
    },
    {
      "username": "4437717",
      "star": "5"
    },
    {
      "username": "47414855",
      "star": "5"
    },
    {
      "username": "47441161",
      "star": "4"
    },
    {
      "username": "hasylin",
      "star": "4"
    },
    {
      "username": "42818733",
      "star": "4"
    },
    {
      "username": "feelgoodinc",
      "star": "5"
    },
    {
      "username": "43300075",
      "star": "5"
    },
    {
      "username": "2350274",
      "star": "4"
    },
    {
      "username": "1142046",
      "star": "4"
    },
    {
      "username": "1787853",
      "star": "4"
    },
    {
      "username": "2242955",
      "star": "4"
    },
    {
      "username": "ending14",
      "star": "4"
    },
    {
      "username": "imkiko",
      "star": "5"
    },
    {
      "username": "2164573",
      "star": "3"
    },
    {
      "username": "goodnightsue",
      "star": "4"
    },
    {
      "username": "jww",
      "star": "5"
    },
    {
      "username": "didifullhouse",
      "star": "4"
    },
    {
      "username": "tucia",
      "star": "5"
    },
    {
      "username": "2321200",
      "star": "5"
    },
    {
      "username": "2836258",
      "star": "4"
    },
    {
      "username": "love.sunnyday",
      "star": "5"
    },
    {
      "username": "jiadele",
      "star": "5"
    },
    {
      "username": "2716000",
      "star": "5"
    },
    {
      "username": "3009581",
      "star": "4"
    },
    {
      "username": "2200276",
      "star": "4"
    },
    {
      "username": "yangxinlian",
      "star": "4"
    },
    {
      "username": "4250324",
      "star": "5"
    },
    {
      "username": "xiaonizibuguai",
      "star": "4"
    },
    {
      "username": "silvani",
      "star": "5"
    },
    {
      "username": "4626170",
      "star": "5"
    },
    {
      "username": "2513758",
      "star": "5"
    },
    {
      "username": "moggie",
      "star": "5"
    },
    {
      "username": "3816667",
      "star": "4"
    },
    {
      "username": "15685644",
      "star": "4"
    },
    {
      "username": "2212176",
      "star": "5"
    },
    {
      "username": "2895863",
      "star": "5"
    },
    {
      "username": "4750804",
      "star": "5"
    },
    {
      "username": "1681391",
      "star": "5"
    },
    {
      "username": "13697129",
      "star": "4"
    },
    {
      "username": "simbashi",
      "star": "5"
    },
    {
      "username": "3651282",
      "star": "5"
    },
    {
      "username": "72067564",
      "star": "5"
    },
    {
      "username": "130543981",
      "star": "4"
    },
    {
      "username": "52390926",
      "star": "4"
    },
    {
      "username": "nancyreighli",
      "star": "5"
    },
    {
      "username": "2885661",
      "star": "5"
    },
    {
      "username": "yeil",
      "star": "5"
    },
    {
      "username": "mrabit",
      "star": "5"
    },
    {
      "username": "1983268",
      "star": "4"
    },
    {
      "username": "1915168",
      "star": "5"
    },
    {
      "username": "3864992",
      "star": "5"
    },
    {
      "username": "2327798",
      "star": "5"
    },
    {
      "username": "1315443",
      "star": "5"
    },
    {
      "username": "EmilyStranger",
      "star": "4"
    },
    {
      "username": "niuke",
      "star": "4"
    },
    {
      "username": "1679168",
      "star": "5"
    },
    {
      "username": "hzqt210",
      "star": "5"
    },
    {
      "username": "1395495",
      "star": "5"
    },
    {
      "username": "jiajia_family",
      "star": "5"
    },
    {
      "username": "3360974",
      "star": "4"
    },
    {
      "username": "fallheart",
      "star": "5"
    },
    {
      "username": "pdstudio",
      "star": "5"
    },
    {
      "username": "1904297",
      "star": "4"
    },
    {
      "username": "3516982",
      "star": "4"
    },
    {
      "username": "1946576",
      "star": "5"
    },
    {
      "username": "2890145",
      "star": "3"
    },
    {
      "username": "GrowingSoil",
      "star": "4"
    },
    {
      "username": "sleepingcat",
      "star": "4"
    },
    {
      "username": "2452092",
      "star": "4"
    },
    {
      "username": "dianfengshan",
      "star": "5"
    },
    {
      "username": "40996722",
      "star": "4"
    },
    {
      "username": "lx461819",
      "star": "4"
    },
    {
      "username": "72117008",
      "star": "4"
    },
    {
      "username": "71813256",
      "star": "5"
    },
    {
      "username": "kaveneli",
      "star": "5"
    },
    {
      "username": "71175136",
      "star": "5"
    },
    {
      "username": "YY.punK",
      "star": "5"
    },
    {
      "username": "Wxizi",
      "star": "5"
    },
    {
      "username": "68292844",
      "star": "4"
    },
    {
      "username": "65117682",
      "star": "5"
    },
    {
      "username": "58898719",
      "star": "5"
    },
    {
      "username": "70549682",
      "star": "5"
    },
    {
      "username": "65822465",
      "star": "1"
    },
    {
      "username": "52355492",
      "star": "4"
    },
    {
      "username": "70050791",
      "star": "4"
    },
    {
      "username": "65685599",
      "star": "5"
    },
    {
      "username": "69776548",
      "star": "4"
    },
    {
      "username": "69512860",
      "star": "5"
    },
    {
      "username": "67703716",
      "star": "5"
    },
    {
      "username": "62401015",
      "star": "4"
    },
    {
      "username": "46124720",
      "star": "5"
    },
    {
      "username": "AngelaYaYa",
      "star": "4"
    },
    {
      "username": "62124460",
      "star": "5"
    },
    {
      "username": "ltmz",
      "star": "4"
    },
    {
      "username": "61304960",
      "star": "4"
    },
    {
      "username": "shankuikui",
      "star": "4"
    },
    {
      "username": "60431088",
      "star": "5"
    },
    {
      "username": "67521342",
      "star": "4"
    },
    {
      "username": "woshiyibafutou",
      "star": "5"
    },
    {
      "username": "63966498",
      "star": "5"
    },
    {
      "username": "40994240",
      "star": "5"
    },
    {
      "username": "65074030",
      "star": "5"
    },
    {
      "username": "63875391",
      "star": "4"
    },
    {
      "username": "2227530",
      "star": "5"
    },
    {
      "username": "64277595",
      "star": "4"
    },
    {
      "username": "jianguonut",
      "star": "4"
    },
    {
      "username": "bensusanlana",
      "star": "5"
    },
    {
      "username": "WellDone",
      "star": "4"
    },
    {
      "username": "81093461",
      "star": "5"
    },
    {
      "username": "66764669",
      "star": "5"
    },
    {
      "username": "76987002",
      "star": "3"
    },
    {
      "username": "4348631",
      "star": "5"
    },
    {
      "username": "44513908",
      "star": "5"
    },
    {
      "username": "76763450",
      "star": "4"
    },
    {
      "username": "80703791",
      "star": "4"
    },
    {
      "username": "69197050",
      "star": "3"
    },
    {
      "username": "64459434",
      "star": "4"
    },
    {
      "username": "69702484",
      "star": "5"
    },
    {
      "username": "71847250",
      "star": "4"
    },
    {
      "username": "60113150",
      "star": "4"
    },
    {
      "username": "78409290",
      "star": "4"
    },
    {
      "username": "33885123",
      "star": "5"
    },
    {
      "username": "foolishwwz",
      "star": "4"
    },
    {
      "username": "74399784",
      "star": "5"
    },
    {
      "username": "59164393",
      "star": "4"
    },
    {
      "username": "87814134",
      "star": "4"
    },
    {
      "username": "58922912",
      "star": "5"
    },
    {
      "username": "85079330",
      "star": "3"
    },
    {
      "username": "85286456",
      "star": "5"
    },
    {
      "username": "Juqa",
      "star": "3"
    },
    {
      "username": "76927727",
      "star": "5"
    },
    {
      "username": "elaine0932",
      "star": "5"
    },
    {
      "username": "72099590",
      "star": "5"
    },
    {
      "username": "5477300",
      "star": "5"
    },
    {
      "username": "66421174",
      "star": "5"
    },
    {
      "username": "69022630",
      "star": "4"
    },
    {
      "username": "readmovie",
      "star": "4"
    },
    {
      "username": "85236229",
      "star": "4"
    },
    {
      "username": "52605343",
      "star": "5"
    },
    {
      "username": "6444551",
      "star": "3"
    },
    {
      "username": "70088060",
      "star": "4"
    },
    {
      "username": "76699769",
      "star": "5"
    },
    {
      "username": "68228693",
      "star": "3"
    },
    {
      "username": "83226461",
      "star": "5"
    },
    {
      "username": "83140290",
      "star": "3"
    },
    {
      "username": "53888583",
      "star": "5"
    },
    {
      "username": "83130131",
      "star": "4"
    },
    {
      "username": "71067402",
      "star": "3"
    },
    {
      "username": "83081516",
      "star": "4"
    },
    {
      "username": "82649279",
      "star": "5"
    },
    {
      "username": "62305828",
      "star": "5"
    },
    {
      "username": "drownings",
      "star": "4"
    },
    {
      "username": "74984723",
      "star": "5"
    },
    {
      "username": "76766697",
      "star": "5"
    },
    {
      "username": "76685969",
      "star": "5"
    },
    {
      "username": "eryao",
      "star": "4"
    },
    {
      "username": "59169512",
      "star": "4"
    },
    {
      "username": "53281610",
      "star": "5"
    },
    {
      "username": "67814811",
      "star": "5"
    },
    {
      "username": "70842317",
      "star": "4"
    },
    {
      "username": "74649840",
      "star": "5"
    },
    {
      "username": "cherish057",
      "star": "4"
    },
    {
      "username": "72873286",
      "star": "4"
    },
    {
      "username": "3211691",
      "star": "5"
    },
    {
      "username": "diskun",
      "star": "4"
    },
    {
      "username": "27865891",
      "star": "5"
    },
    {
      "username": "73477492",
      "star": "4"
    },
    {
      "username": "64330187",
      "star": "5"
    },
    {
      "username": "anran1207",
      "star": "5"
    },
    {
      "username": "72369976",
      "star": "4"
    },
    {
      "username": "65509729",
      "star": "5"
    },
    {
      "username": "anran1207",
      "star": "4"
    },
    {
      "username": "w7221",
      "star": "5"
    },
    {
      "username": "79994093",
      "star": "5"
    },
    {
      "username": "63328880",
      "star": "4"
    },
    {
      "username": "dmbg",
      "star": "5"
    },
    {
      "username": "113669205",
      "star": "4"
    },
    {
      "username": "104288200",
      "star": "4"
    },
    {
      "username": "104288200",
      "star": "4"
    },
    {
      "username": "104288200",
      "star": "4"
    },
    {
      "username": "104288200",
      "star": "5"
    },
    {
      "username": "103428481",
      "star": "5"
    },
    {
      "username": "68077135",
      "star": "4"
    },
    {
      "username": "oncechen",
      "star": "4"
    },
    {
      "username": "73760193",
      "star": "4"
    },
    {
      "username": "101914591",
      "star": 0
    },
    {
      "username": "75001593",
      "star": 0
    },
    {
      "username": "98364565",
      "star": "5"
    },
    {
      "username": "43290606",
      "star": "4"
    },
    {
      "username": "47474748",
      "star": "5"
    },
    {
      "username": "95722305",
      "star": "5"
    },
    {
      "username": "73038750",
      "star": "5"
    },
    {
      "username": "73038750",
      "star": "5"
    },
    {
      "username": "73038750",
      "star": "5"
    },
    {
      "username": "49136461",
      "star": "5"
    },
    {
      "username": "94619437",
      "star": "5"
    },
    {
      "username": "91887169",
      "star": "4"
    },
    {
      "username": "78651058",
      "star": "5"
    },
    {
      "username": "40518865",
      "star": "5"
    },
    {
      "username": "58388353",
      "star": "4"
    },
    {
      "username": "91994189",
      "star": "5"
    },
    {
      "username": "125047805",
      "star": "4"
    },
    {
      "username": "135488195",
      "star": "4"
    },
    {
      "username": "134643942",
      "star": "5"
    },
    {
      "username": "64260590",
      "star": "4"
    },
    {
      "username": "131936664",
      "star": "4"
    },
    {
      "username": "72352588",
      "star": "4"
    },
    {
      "username": "44348634",
      "star": "4"
    },
    {
      "username": "132036462",
      "star": "5"
    },
    {
      "username": "132036462",
      "star": "5"
    },
    {
      "username": "132036462",
      "star": "5"
    },
    {
      "username": "131953647",
      "star": "4"
    },
    {
      "username": "131953647",
      "star": "4"
    },
    {
      "username": "128847202",
      "star": "5"
    },
    {
      "username": "lin954086738",
      "star": "4"
    },
    {
      "username": "lin954086738",
      "star": "4"
    },
    {
      "username": "93404333",
      "star": "4"
    },
    {
      "username": "66131979",
      "star": "5"
    },
    {
      "username": "76760318",
      "star": "5"
    },
    {
      "username": "2559020",
      "star": "4"
    },
    {
      "username": "51057713",
      "star": "4"
    },
    {
      "username": "jiaheeee",
      "star": "4"
    },
    {
      "username": "122741814",
      "star": "4"
    },
    {
      "username": "123586799",
      "star": "5"
    },
    {
      "username": "122843315",
      "star": "5"
    },
    {
      "username": "128123751",
      "star": "4"
    },
    {
      "username": "51704921",
      "star": "5"
    },
    {
      "username": "CrylicHoo",
      "star": "4"
    },
    {
      "username": "106366318",
      "star": "4"
    },
    {
      "username": "74802196",
      "star": "5"
    },
    {
      "username": "soloose",
      "star": "4"
    },
    {
      "username": "74612234",
      "star": "4"
    },
    {
      "username": "81361903",
      "star": "5"
    },
    {
      "username": "81969223",
      "star": "5"
    },
    {
      "username": "116856715",
      "star": "5"
    },
    {
      "username": "81968893",
      "star": "4"
    },
    {
      "username": "lenazhu",
      "star": "4"
    },
    {
      "username": "Xylon.Yu",
      "star": "5"
    },
    {
      "username": "nowhereelse",
      "star": "3"
    },
    {
      "username": "2014077",
      "star": "3"
    },
    {
      "username": "25618328",
      "star": "3"
    },
    {
      "username": "diamondli",
      "star": "3"
    },
    {
      "username": "ideal",
      "star": "5"
    },
    {
      "username": "Linth",
      "star": "3"
    },
    {
      "username": "1164703",
      "star": "5"
    },
    {
      "username": "potter",
      "star": "5"
    },
    {
      "username": "grantxie",
      "star": "5"
    },
    {
      "username": "4270931",
      "star": "5"
    },
    {
      "username": "youhebi",
      "star": "5"
    }
  ],
  "title": ""
}